[
  { "id": "tg-1", "pattern": "Present Perfect", "structure": "S + have/has + V3/ed", "meaning": "Thì hiện tại hoàn thành", "example": "I have worked here for 5 years.", "exampleTranslation": "Tôi đã làm việc ở đây 5 năm.", "difficulty": "intermediate", "blankedExample": "I _____ (work) here for 5 years." },
  { "id": "tg-2", "pattern": "Past Perfect", "structure": "S + had + V3/ed", "meaning": "Thì quá khứ hoàn thành", "example": "She had already left when I arrived.", "exampleTranslation": "Cô ấy đã rời đi khi tôi đến.", "difficulty": "advanced", "blankedExample": "She _____ (already leave) when I arrived." },
  { "id": "tg-3", "pattern": "Future Perfect", "structure": "S + will have + V3/ed", "meaning": "Thì tương lai hoàn thành", "example": "By next year, we will have completed the project.", "exampleTranslation": "Đến năm sau, chúng tôi sẽ hoàn thành dự án.", "difficulty": "advanced", "blankedExample": "By next year, we _____ (complete) the project." },
  { "id": "tg-4", "pattern": "Present Perfect Continuous", "structure": "S + have/has + been + V-ing", "meaning": "Hiện tại hoàn thành tiếp diễn", "example": "I have been working on this report all morning.", "exampleTranslation": "Tôi đã làm báo cáo này cả buổi sáng.", "difficulty": "advanced", "blankedExample": "I _____ (work) on this report all morning." },
  { "id": "tg-5", "pattern": "Simple Past vs. Present Perfect", "structure": "V2/ed vs. have/has + V3/ed", "meaning": "So sánh quá khứ đơn và hiện tại hoàn thành", "example": "I visited Paris last year. / I have visited Paris twice.", "exampleTranslation": "Tôi đã thăm Paris năm ngoái. / Tôi đã thăm Paris hai lần.", "difficulty": "intermediate", "blankedExample": "I _____ (visit) Paris last year." },
  { "id": "tg-6", "pattern": "Relative Clauses (Who/Which/That)", "structure": "N + relative pronoun + clause", "meaning": "Mệnh đề quan hệ", "example": "The man who called you is my manager.", "exampleTranslation": "Người đàn ông mà gọi cho bạn là quản lý của tôi.", "difficulty": "intermediate", "blankedExample": "The man _____ called you is my manager." },
  { "id": "tg-7", "pattern": "Passive Voice", "structure": "be + V3/ed", "meaning": "Câu bị động", "example": "The report was written by John.", "exampleTranslation": "Bản báo cáo được viết bởi John.", "difficulty": "intermediate", "blankedExample": "The report _____ (write) by John." },
  { "id": "tg-8", "pattern": "Conditionals (Type 1, 2, 3)", "structure": "If + clause, main clause", "meaning": "Câu điều kiện loại 1, 2, 3", "example": "If it rains, we will cancel the meeting.", "exampleTranslation": "Nếu trời mưa, chúng tôi sẽ hủy cuộc họp.", "difficulty": "advanced", "blankedExample": "If it rains, we _____ (cancel) the meeting." },
  { "id": "tg-9", "pattern": "Reported Speech", "structure": "S + said that + clause", "meaning": "Câu tường thuật", "example": "He said that he was tired.", "exampleTranslation": "Anh ấy nói rằng anh ấy mệt.", "difficulty": "intermediate", "blankedExample": "He said that he _____ (be) tired." },
  { "id": "tg-10", "pattern": "Gerunds vs. Infinitives", "structure": "V + V-ing vs. V + to V", "meaning": "Danh động từ và động từ nguyên thể", "example": "I enjoy reading books. / I want to read a book.", "exampleTranslation": "Tôi thích đọc sách. / Tôi muốn đọc một cuốn sách.", "difficulty": "intermediate", "blankedExample": "I enjoy _____ (read) books." },
  { "id": "tg-11", "pattern": "Modal Verbs", "structure": "Modal verb + V", "meaning": "Động từ khuyết thiếu", "example": "You must finish this by tomorrow.", "exampleTranslation": "Bạn phải hoàn thành việc này trước ngày mai.", "difficulty": "beginner", "blankedExample": "You _____ finish this by tomorrow." },
  { "id": "tg-12", "pattern": "Prepositions of Time/Place", "structure": "in, on, at", "meaning": "Giới từ chỉ thời gian/nơi chốn", "example": "The meeting is on Monday at 9 AM in the conference room.", "exampleTranslation": "Cuộc họp vào thứ Hai lúc 9 giờ sáng ở phòng hội nghị.", "difficulty": "beginner", "blankedExample": "The meeting is _____ Monday at 9 AM." },
  { "id": "tg-13", "pattern": "Conjunctions", "structure": "and, but, or, so", "meaning": "Liên từ", "example": "I like coffee, but my sister prefers tea.", "exampleTranslation": "Tôi thích cà phê, nhưng em gái tôi thích trà.", "difficulty": "beginner", "blankedExample": "I like coffee, _____ my sister prefers tea." },
  { "id": "tg-14", "pattern": "Articles (a, an, the)", "structure": "a/an/the + N", "meaning": "Mạo từ", "example": "I saw a movie. The movie was great.", "exampleTranslation": "Tôi đã xem một bộ phim. Bộ phim đó rất hay.", "difficulty": "beginner", "blankedExample": "I saw _____ movie. The movie was great." },
  { "id": "tg-15", "pattern": "Comparatives & Superlatives", "structure": "more/most + adj/adv", "meaning": "So sánh hơn và so sánh nhất", "example": "This book is more interesting than that one.", "exampleTranslation": "Cuốn sách này thú vị hơn cuốn sách kia.", "difficulty": "intermediate", "blankedExample": "This book is _____ (interesting) than that one." },
  { "id": "tg-16", "pattern": "Causative Verbs", "structure": "have/get + O + V3/ed", "meaning": "Cấu trúc nhờ vả, bắt buộc", "example": "I had my car fixed.", "exampleTranslation": "Tôi đã mang xe đi sửa.", "difficulty": "advanced", "blankedExample": "I had my car _____ (fix)." },
  { "id": "tg-17", "pattern": "Subjunctive Mood", "structure": "suggest/demand that S + V", "meaning": "Câu giả định", "example": "It is essential that he arrive on time.", "exampleTranslation": "Điều cần thiết là anh ấy phải đến đúng giờ.", "difficulty": "advanced", "blankedExample": "It is essential that he _____ (arrive) on time." },
  { "id": "tg-18", "pattern": "Inversion", "structure": "Never/Hardly + auxiliary + S + V", "meaning": "Đảo ngữ", "example": "Never have I seen such a beautiful sunset.", "exampleTranslation": "Chưa bao giờ tôi thấy cảnh hoàng hôn đẹp như vậy.", "difficulty": "advanced", "blankedExample": "Never _____ (I see) such a beautiful sunset." },
  { "id": "tg-19", "pattern": "Participle Clauses", "structure": "V-ing / V3/ed + clause", "meaning": "Mệnh đề phân từ", "example": "Feeling tired, she went to bed early.", "exampleTranslation": "Cảm thấy mệt, cô ấy đi ngủ sớm.", "difficulty": "advanced", "blankedExample": "_____ (feel) tired, she went to bed early." },
  { "id": "tg-20", "pattern": "Used to / Be used to", "structure": "used to + V / be used to + V-ing", "meaning": "Đã từng / Quen với việc", "example": "I used to wake up early. / I am used to waking up early.", "exampleTranslation": "Tôi đã từng dậy sớm. / Tôi quen với việc dậy sớm.", "difficulty": "intermediate", "blankedExample": "I am _____ (used to / wake) up early." },
  { "id": "tg-21", "pattern": "Simple Present Tense", "structure": "S + V(s/es)", "meaning": "Thì hiện tại đơn", "example": "The company holds meetings every Monday.", "exampleTranslation": "Công ty tổ chức cuộc họp mỗi thứ Hai.", "difficulty": "beginner", "blankedExample": "The company _____ (hold) meetings every Monday." },
  { "id": "tg-22", "pattern": "Simple Past Tense", "structure": "S + V2/ed", "meaning": "Thì quá khứ đơn", "example": "I submitted the report yesterday.", "exampleTranslation": "Tôi đã nộp báo cáo hôm qua.", "difficulty": "beginner", "blankedExample": "I _____ (submit) the report yesterday." },
  { "id": "tg-23", "pattern": "Simple Future Tense", "structure": "S + will + V", "meaning": "Thì tương lai đơn", "example": "We will launch the new product next week.", "exampleTranslation": "Chúng tôi sẽ ra mắt sản phẩm mới tuần sau.", "difficulty": "beginner", "blankedExample": "We _____ (launch) the new product next week." },
  { "id": "tg-24", "pattern": "Present Continuous Tense", "structure": "S + am/is/are + V-ing", "meaning": "Thì hiện tại tiếp diễn", "example": "She is preparing the presentation now.", "exampleTranslation": "Cô ấy đang chuẩn bị bài thuyết trình bây giờ.", "difficulty": "beginner", "blankedExample": "She _____ (prepare) the presentation now." },
  { "id": "tg-25", "pattern": "Past Continuous Tense", "structure": "S + was/were + V-ing", "meaning": "Thì quá khứ tiếp diễn", "example": "I was working on the budget when the phone rang.", "exampleTranslation": "Tôi đang làm việc trên ngân sách khi điện thoại đổ chuông.", "difficulty": "beginner", "blankedExample": "I _____ (work) on the budget when the phone rang." },
  { "id": "tg-26", "pattern": "Plural Nouns and Subject-Verb Agreement", "structure": "S (plural) + V (plural form)", "meaning": "Số nhiều và sự hòa hợp chủ ngữ - vị ngữ", "example": "The employees are attending the training session.", "exampleTranslation": "Các nhân viên đang tham gia buổi đào tạo.", "difficulty": "beginner", "blankedExample": "The employees _____ (attend) the training session." },
  { "id": "tg-27", "pattern": "Possessive Pronouns", "structure": "my/your/his/her + N", "meaning": "Đại từ sở hữu", "example": "This is my desk, and that is her computer.", "exampleTranslation": "Đây là bàn của tôi, và đó là máy tính của cô ấy.", "difficulty": "beginner", "blankedExample": "This is _____ desk, and that is _____ computer." },
  { "id": "tg-28", "pattern": "Demonstratives", "structure": "this/that/these/those + N", "meaning": "Chỉ định", "example": "This document is important, and those files are outdated.", "exampleTranslation": "Tài liệu này quan trọng, và các tệp đó đã lỗi thời.", "difficulty": "beginner", "blankedExample": "_____ document is important, and _____ files are outdated." },
  { "id": "tg-29", "pattern": "Quantifiers", "structure": "some/any/much/many/a lot of + N", "meaning": "Từ chỉ số lượng", "example": "We have some budget left, but we need more.", "exampleTranslation": "Chúng ta còn một ít ngân sách, nhưng cần thêm.", "difficulty": "beginner", "blankedExample": "We have _____ budget left, but we need more." },
  { "id": "tg-30", "pattern": "Question Words", "structure": "Wh-word + auxiliary + S + V?", "meaning": "Từ để hỏi", "example": "Who is responsible for this project?", "exampleTranslation": "Ai chịu trách nhiệm cho dự án này?", "difficulty": "beginner", "blankedExample": "_____ is responsible for this project?" },
  { "id": "tg-31", "pattern": "Present Perfect vs. Past Simple", "structure": "have/has + V3/ed vs. V2/ed", "meaning": "So sánh hiện tại hoàn thành và quá khứ đơn", "example": "I have already finished the report. / I finished it last night.", "exampleTranslation": "Tôi đã hoàn thành báo cáo rồi. / Tôi hoàn thành nó tối qua.", "difficulty": "intermediate", "blankedExample": "I _____ (already finish) the report." },
  { "id": "tg-32", "pattern": "Future Continuous Tense", "structure": "S + will be + V-ing", "meaning": "Thì tương lai tiếp diễn", "example": "This time tomorrow, I will be flying to New York.", "exampleTranslation": "Đúng lúc này ngày mai, tôi sẽ đang bay đến New York.", "difficulty": "intermediate", "blankedExample": "This time tomorrow, I _____ (fly) to New York." },
  { "id": "tg-33", "pattern": "Used to vs. Would", "structure": "used to + V / would + V (past habits)", "meaning": "So sánh 'đã từng' và 'thường làm' trong quá khứ", "example": "I used to work late. / I would often work late.", "exampleTranslation": "Tôi đã từng làm việc muộn. / Tôi thường làm việc muộn.", "difficulty": "intermediate", "blankedExample": "I _____ (used to / work) late." },
  { "id": "tg-34", "pattern": "Phrasal Verbs", "structure": "V + preposition/adverb", "meaning": "Cụm động từ thông dụng trong kinh doanh", "example": "We need to set up a meeting.", "exampleTranslation": "Chúng ta cần tổ chức một cuộc họp.", "difficulty": "intermediate", "blankedExample": "We need to _____ (set up) a meeting." },
  { "id": "tg-35", "pattern": "Conditional Type 0", "structure": "If + present simple, present simple", "meaning": "Câu điều kiện loại 0 (sự thật chung)", "example": "If you heat water, it boils.", "exampleTranslation": "Nếu bạn đun nóng nước, nó sẽ sôi.", "difficulty": "intermediate", "blankedExample": "If you heat water, it _____ (boil)." },
  { "id": "tg-36", "pattern": "Reported Speech with Questions", "structure": "S + asked + (if/whether) + clause", "meaning": "Câu tường thuật với câu hỏi", "example": "She asked if the meeting was scheduled.", "exampleTranslation": "Cô ấy hỏi liệu cuộc họp đã được lên lịch chưa.", "difficulty": "intermediate", "blankedExample": "She asked _____ the meeting _____ (schedule)." },
  { "id": "tg-37", "pattern": "Wish + Past Simple", "structure": "S + wish(es) + past simple", "meaning": "Wish với thì quá khứ đơn (ước muốn hiện tại)", "example": "I wish I had more time.", "exampleTranslation": "Tôi ước tôi có nhiều thời gian hơn.", "difficulty": "intermediate", "blankedExample": "I wish I _____ (have) more time." },
  { "id": "tg-38", "pattern": "Wish + Past Perfect", "structure": "S + wish(es) + had + V3/ed", "meaning": "Wish với thì quá khứ hoàn thành (ước muốn quá khứ)", "example": "She wishes she had studied harder.", "exampleTranslation": "Cô ấy ước cô ấy đã học chăm chỉ hơn.", "difficulty": "intermediate", "blankedExample": "She wishes she _____ (study) harder." },
  { "id": "tg-39", "pattern": "So / Such...that", "structure": "so + adj/adv / such + (a/an) + N + that", "meaning": "Quá...đến nỗi", "example": "The project was so complex that we needed extra resources.", "exampleTranslation": "Dự án quá phức tạp đến nỗi chúng tôi cần thêm nguồn lực.", "difficulty": "intermediate", "blankedExample": "The project was _____ complex _____ we needed extra resources." },
  { "id": "tg-40", "pattern": "Although / Despite / In spite of", "structure": "Although + clause / Despite/In spite of + N/V-ing", "meaning": "Mặc dù", "example": "Although we were late, we finished the presentation.", "exampleTranslation": "Mặc dù chúng tôi đến muộn, chúng tôi đã hoàn thành bài thuyết trình.", "difficulty": "intermediate", "blankedExample": "_____ we were late, we finished the presentation." },
  { "id": "tg-41", "pattern": "Both...and / Either...or / Neither...nor", "structure": "both A and B / either A or B / neither A nor B", "meaning": "Cả...và / Hoặc...hoặc / Không...cũng không", "example": "Both the manager and the supervisor approved the plan.", "exampleTranslation": "Cả quản lý và giám sát viên đều phê duyệt kế hoạch.", "difficulty": "intermediate", "blankedExample": "_____ the manager _____ the supervisor approved the plan." },
  { "id": "tg-42", "pattern": "too...to / enough...to", "structure": "too + adj + to V / adj + enough + to V", "meaning": "Quá...để / Đủ...để", "example": "The report is too long to read in one sitting.", "exampleTranslation": "Báo cáo quá dài để đọc một lần.", "difficulty": "intermediate", "blankedExample": "The report is _____ long _____ read in one sitting." },
  { "id": "tg-43", "pattern": "Verb + Gerund vs. Verb + Infinitive", "structure": "V + V-ing / V + to V", "meaning": "Động từ tiếp theo danh động từ hoặc nguyên thể (trường hợp cụ thể)", "example": "I remember locking the door. / I remember to lock the door.", "exampleTranslation": "Tôi nhớ là tôi đã khóa cửa. / Tôi nhớ để khóa cửa.", "difficulty": "intermediate", "blankedExample": "I remember _____ (lock) the door." },
  { "id": "tg-44", "pattern": "Used to / Be used to / Get used to", "structure": "used to + V / be used to + V-ing / get used to + V-ing", "meaning": "Đã từng / Quen với việc / Quen dần với việc", "example": "I used to commute by bus. Now I am used to driving.", "exampleTranslation": "Tôi đã từng đi xe buýt đi làm. Bây giờ tôi quen với việc lái xe.", "difficulty": "intermediate", "blankedExample": "I _____ (used to / commute) by bus." },
  { "id": "tg-45", "pattern": "Cleft Sentences", "structure": "It + be + emphasized part + that/who + clause", "meaning": "Câu chẻ (nhấn mạnh)", "example": "It was John who finished the project.", "exampleTranslation": "Chính John là người đã hoàn thành dự án.", "difficulty": "intermediate", "blankedExample": "It was John _____ finished the project." },
  { "id": "tg-46", "pattern": "Mixed Conditionals", "structure": "If + past perfect, would + V / If + past simple, would have + V3/ed", "meaning": "Câu điều kiện hỗn hợp", "example": "If I had studied harder, I would be in a better position now.", "exampleTranslation": "Nếu tôi đã học chăm chỉ hơn, tôi sẽ ở vị trí tốt hơn bây giờ.", "difficulty": "advanced", "blankedExample": "If I _____ (study) harder, I would be in a better position now." },
  { "id": "tg-47", "pattern": "Inversion with Negative Adverbs", "structure": "Rarely/Seldom/Not only + auxiliary + S + V", "meaning": "Đảo ngữ với trạng từ phủ định", "example": "Rarely do we encounter such a dedicated team.", "exampleTranslation": "Hiếm khi chúng ta gặp một đội nhóm tận tâm như vậy.", "difficulty": "advanced", "blankedExample": "Rarely _____ (we encounter) such a dedicated team." },
  { "id": "tg-48", "pattern": "Bare Infinitive after Modal Verbs", "structure": "modal + have + V3/ed", "meaning": "Nguyên thể trần sau động từ khuyết thiếu", "example": "You should have informed me earlier.", "exampleTranslation": "Bạn nên đã thông báo cho tôi sớm hơn.", "difficulty": "advanced", "blankedExample": "You _____ (should have inform) me earlier." },
  { "id": "tg-49", "pattern": "Perfect Gerunds", "structure": "Having + V3/ed + ...", "meaning": "Danh động từ hoàn thành", "example": "Having completed the task, she reported to the manager.", "exampleTranslation": "Sau khi hoàn thành nhiệm vụ, cô ấy báo cáo cho quản lý.", "difficulty": "advanced", "blankedExample": "_____ (complete) the task, she reported to the manager." },
  { "id": "tg-50", "pattern": "Advanced Passive Voice", "structure": "get + V3/ed", "meaning": "Câu bị động nâng cao", "example": "The project got delayed due to unforeseen issues.", "exampleTranslation": "Dự án bị trì hoãn do các vấn đề không lường trước.", "difficulty": "advanced", "blankedExample": "The project _____ (delay) due to unforeseen issues." },
  { "id": "tg-51", "pattern": "Causative Have/Get", "structure": "have/get + O + V3/ed / have/get + O + V", "meaning": "Cấu trúc causative (nhờ vả, bắt buộc)", "example": "I need to get the document signed.", "exampleTranslation": "Tôi cần làm cho tài liệu được ký.", "difficulty": "advanced", "blankedExample": "I need to _____ (get) the document signed." },
  { "id": "tg-52", "pattern": "Advanced Relative Clauses", "structure": "N + whose/where/which + clause", "meaning": "Mệnh đề quan hệ nâng cao", "example": "The employee whose performance improved got a promotion.", "exampleTranslation": "Nhân viên mà hiệu suất cải thiện đã được thăng chức.", "difficulty": "advanced", "blankedExample": "The employee _____ performance improved got a promotion." },
  { "id": "tg-53", "pattern": "Nominal Clauses", "structure": "what/whoever/whatever + clause", "meaning": "Mệnh đề danh ngữ", "example": "What we need is more data.", "exampleTranslation": "Điều chúng ta cần là thêm dữ liệu.", "difficulty": "advanced", "blankedExample": "_____ we need is more data." },
  { "id": "tg-54", "pattern": "Advanced Reported Speech", "structure": "S + reported verb + indirect question/command/statement", "meaning": "Câu tường thuật nâng cao", "example": "He explained how to use the software.", "exampleTranslation": "Anh ấy giải thích cách sử dụng phần mềm.", "difficulty": "advanced", "blankedExample": "He explained _____ to use the software." },
  { "id": "tg-55", "pattern": "Ellipsis and Substitution", "structure": "omission of repeated words or substitution with do/so/one", "meaning": "Bỏ sót và thay thế", "example": "I will attend the meeting, and so will she.", "exampleTranslation": "Tôi sẽ tham gia cuộc họp, và cô ấy cũng sẽ tham gia.", "difficulty": "advanced", "blankedExample": "I will attend the meeting, and _____ will she." },
  { "id": "tg-56", "pattern": "Emphatic Structures", "structure": "do/does/did + V", "meaning": "Cấu trúc nhấn mạnh", "example": "I do appreciate your help.", "exampleTranslation": "Tôi thực sự đánh giá cao sự giúp đỡ của bạn.", "difficulty": "advanced", "blankedExample": "I _____ (do) appreciate your help." },
  { "id": "tg-57", "pattern": "Advanced Connectors", "structure": "furthermore/moreover/nevertheless + clause", "meaning": "Liên từ nâng cao", "example": "The results are promising; furthermore, they exceed expectations.", "exampleTranslation": "Kết quả rất khả quan; hơn nữa, chúng vượt quá kỳ vọng.", "difficulty": "advanced", "blankedExample": "The results are promising; _____ they exceed expectations." },
  { "id": "tg-58", "pattern": "Conditional Inversion", "structure": "Had + S + V3/ed / Were + S + to V", "meaning": "Đảo ngữ câu điều kiện", "example": "Had I known about the issue, I would have prepared.", "exampleTranslation": "Nếu tôi đã biết về vấn đề, tôi đã chuẩn bị.", "difficulty": "advanced", "blankedExample": "_____ I known about the issue, I would have prepared." },
  { "id": "tg-59", "pattern": "Advanced Prepositions", "structure": "despite/regarding/concerning + N/V-ing", "meaning": "Giới từ nâng cao", "example": "Despite the budget constraints, we proceeded.", "exampleTranslation": "Bất chấp hạn chế ngân sách, chúng tôi vẫn tiến hành.", "difficulty": "advanced", "blankedExample": "_____ the budget constraints, we proceeded." },
  { "id": "tg-60", "pattern": "Discourse Markers", "structure": "however/therefore/consequently + clause", "meaning": "Từ nối diễn ngôn", "example": "The plan failed; however, we learned from it.", "exampleTranslation": "Kế hoạch thất bại; tuy nhiên, chúng tôi đã học được từ nó.", "difficulty": "advanced", "blankedExample": "The plan failed; _____ we learned from it." }
]
